pydoer/__init__.py
pydoer/commands.py
pydoer/doerrc
pydoer/menu_creator.py
pydoer/notification.py
pydoer/subclass_registry.py
pydoer/terminal_spawner.py
pydoer/windows.py
pydoer-1.0.2.dist-info/LICENSE.txt
pydoer-1.0.2.dist-info/METADATA
pydoer-1.0.2.dist-info/WHEEL
pydoer-1.0.2.dist-info/entry_points.txt
pydoer-1.0.2.dist-info/top_level.txt
pydoer-1.0.2.dist-info/RECORD
