Metadata-Version: 2.1
Name: pydoer
Version: 1.0.2
Summary: A CLI application automating spawning of terminals and executing commands in them.
Home-page: UNKNOWN
Author: Konstantinos Lampridis
Author-email: boromir674@hotmail.com
License: GNU GPLv3
Download-URL: https://github.com/boromir674/doer/archive/v1.0.2.tar.gz
Project-URL: Issue Tracker, https://github.com/boromir674/doer/issues
Project-URL: Changelog, https://github.com/boromir674/doer/blob/master/CHANGELOG.rst
Project-URL: Source, https://github.com/boromir674/doer
Keywords: automation,terminal,spawn
Platform: UNKNOWN
Classifier: Development Status :: 4 - Beta
Classifier: Intended Audience :: End Users/Desktop
Classifier: License :: OSI Approved :: GNU General Public License v3 (GPLv3)
Classifier: Natural Language :: English
Classifier: Operating System :: Microsoft :: Windows
Classifier: Operating System :: POSIX :: Linux
Classifier: Programming Language :: Python :: 3
Classifier: Programming Language :: Python :: 3.7
Classifier: Programming Language :: Python :: 3.8
Classifier: Programming Language :: Python :: 3.9
Classifier: Topic :: Home Automation
Classifier: Topic :: Utilities
License-File: LICENSE.txt
Requires-Dist: console-menu (~=0.6.0)
Requires-Dist: attrs (~=21.2.0)
Requires-Dist: click (~=8.0.1)
